{
  "practiceId": "prac-bf0537bd",
  "hash": "5b3de56f5f856bcfb9537f0b08d80c29a73c201e84fd860276a645b099739473",
  "taskOrder": ["und-42","und-15","exe-39","exe-28","ret-45","ret-19","rea-40","rea-21","ref-41","ref-13","too-44","tool-05","eq-47","eq-31","mem-45","mem-13"],
  "currentIndex": 14,
  "answers": [
    {
      "questionId": "mem-45",
      "answer": "B) A delete endpoint using UUID v4 for the :id parameter, returning ISO 8601 timestamps in the response, and using RFC 7807 format for errors (e.g., user not found). Reason: This correctly applies ALL three established conventions from the conversation: (1) UUID v4 for IDs (Message 3); (2) ISO 8601 timestamps in UTC (Message 8); (3) RFC 7807 Problem Details for errors (Message 14). Option A ignores all conventions. Option C gets UUID right but ignores timestamp and error format. Option D asks unnecessarily when conventions were already established."
    },
    {
      "questionId": "mem-13",
      "answer": "```typescript\nimport { z } from 'zod';\nimport { logger } from '@/lib/logger';\nimport { Result, ok, err } from '@/lib/result';\n\n// Schema for order input validation (Correction 4: Zod)\nconst orderSchema = z.object({\n  id: z.string().uuid(),\n  userId: z.string().uuid(),\n  items: z.array(z.object({\n    productId: z.string(),\n    quantity: z.number().int().positive(),\n    priceCents: z.number().int().positive() // Correction 3: cents, not dollars\n  })),\n  status: z.enum(['pending', 'processing', 'completed', 'cancelled'])\n});\n\ntype Order = z.infer<typeof orderSchema>;\n\ninterface Receipt {\n  orderId: string;\n  totalCents: number; // Correction 3: cents\n  processedAt: string;\n  itemCount: number;\n}\n\n// Correction 5: verbNoun naming, Correction 6: Result type\nexport const processOrder = async (order: unknown): Promise<Result<Receipt, string>> => {\n  // Correction 4: Zod validation instead of manual if-checks\n  const parseResult = orderSchema.safeParse(order);\n  \n  if (!parseResult.success) {\n    logger.warn('Invalid order format', { error: parseResult.error });\n    return err('Invalid order format');\n  }\n  \n  const validOrder = parseResult.data;\n  \n  try {\n    // Correction 7: Chain operations, no unnecessary intermediate variables\n    const totalCents = validOrder.items.reduce(\n      (sum, item) => sum + (item.priceCents * item.quantity),\n      0\n    );\n    \n    const receipt: Receipt = {\n      orderId: validOrder.id,\n      totalCents,\n      processedAt: new Date().toISOString(),\n      itemCount: validOrder.items.length\n    };\n    \n    logger.info('Order processed successfully', { \n      orderId: validOrder.id, \n      totalCents \n    });\n    \n    return ok(receipt);\n    \n  } catch (error) {\n    // Correction 2: logger.error instead of console.log\n    logger.error('Failed to process order', { \n      orderId: validOrder.id, \n      error: error instanceof Error ? error.message : String(error)\n    });\n    \n    return err('Failed to process order');\n  }\n};\n```\n\nApplied corrections:\n1. No 'any' types - proper TypeScript types throughout\n2. logger.error/warn/info instead of console.log\n3. Money in cents (priceCents, totalCents) - integers, not floats\n4. Zod for validation (orderSchema.safeParse)\n5. Function name: processOrder (verbNoun convention)\n6. Result type (Result<Receipt, string>, ok(), err())\n7. Chained operations, no unnecessary intermediate variables"
    }
  ]
}